char_converter/__init__.py
char_converter/converter.py
char_converter/data/v2s.msgpack
char_converter/data/v2t.msgpack
char_converter-0.51.dist-info/licenses/LICENSE
char_converter-0.51.dist-info/METADATA
char_converter-0.51.dist-info/WHEEL
char_converter-0.51.dist-info/top_level.txt
char_converter-0.51.dist-info/RECORD
