Metadata-Version: 2.4
Name: char_converter
Version: 0.51
Summary: A library to convert variant Chinese characters to standard simplified or traditional characters.
Author: Yuqi Chen
Author-email: chenyuqi@hku.hk
License-File: LICENSE
Requires-Dist: msgpack
Requires-Dist: setuptools
Dynamic: author
Dynamic: author-email
Dynamic: description
Dynamic: description-content-type
Dynamic: license-file
Dynamic: requires-dist
Dynamic: summary
